diffract/__init__.py
diffract/__main__.py
diffract/__version__.py
diffract/core.py
diffract-0.1.1.dist-info/LICENSE
diffract-0.1.1.dist-info/METADATA
diffract-0.1.1.dist-info/WHEEL
diffract-0.1.1.dist-info/entry_points.txt
diffract-0.1.1.dist-info/RECORD
